decoder_demos/__init__.py
decoder_demos/decoding_utils.py
decoder_demos/ensongdec_decoder.py
decoder_demos/ensongdec_sample.py
decoder_demos/filtering.py
decoder_demos/ndt2_sample.py
decoder_demos/random_decoder.py
decoder_demos/sklearn_decoder.py
decoder_demos/sklearn_sample.py
falcon_challenge/__init__.py
falcon_challenge/challenge_runner.py
falcon_challenge/config.py
falcon_challenge/dataloaders.py
falcon_challenge/evaluator.py
falcon_challenge/interface.py
falcon_challenge-1.0.2.dist-info/licenses/LICENSE
preproc/__init__.py
preproc/assemble_data.py
preproc/b1_falcon_utils.py
preproc/b1_nwb_utils.py
preproc/b1_preproc.py
preproc/filtering.py
preproc/h2_preproc.py
preproc/m1_fewshot_trial_counts.py
preproc/m1_reachgrasp_preprocv2.py
preproc/m2_fewshot_trial_counts.py
preproc/m2_fullband.py
preproc/m2_preproc.py
preproc/merge_answers.py
preproc/nwb_create_utils.py
preproc/wrapper_convert_batch.py
preproc/zip_data.py
falcon_challenge-1.0.2.dist-info/METADATA
falcon_challenge-1.0.2.dist-info/WHEEL
falcon_challenge-1.0.2.dist-info/top_level.txt
falcon_challenge-1.0.2.dist-info/RECORD
