Metadata-Version: 2.4
Name: falcon_challenge
Version: 1.0.2
Home-page: https://github.com/snel-repo/stability-benchmark
Author: Joel Ye
Author-email: joelye9@gmail.com
License-File: LICENSE
Requires-Dist: numpy
Requires-Dist: hydra-core
Requires-Dist: matplotlib
Requires-Dist: tqdm
Requires-Dist: scipy
Requires-Dist: pandas
Requires-Dist: seaborn
Requires-Dist: scikit-learn
Requires-Dist: pynwb
Requires-Dist: torch
Requires-Dist: edit_distance
Requires-Dist: dandi
Dynamic: author
Dynamic: author-email
Dynamic: description
Dynamic: description-content-type
Dynamic: home-page
Dynamic: license-file
Dynamic: requires-dist
